main.py
nape-1.0.0.dist-info/LICENSE
nape-1.0.0.dist-info/METADATA
nape-1.0.0.dist-info/WHEEL
nape-1.0.0.dist-info/entry_points.txt
nape-1.0.0.dist-info/top_level.txt
nape-1.0.0.dist-info/RECORD
