Metadata-Version: 2.1
Name: nape
Version: 1.0.0
Summary: The NAPE Evaluator (nape-eval) is a CLI used by the NAPE CLI to apply Test of Details against a given piece of evidence to assess if a Control Action passes, failes, or is inconclusive.
Author-email: Bill Bensing <bill@napecentral.com>
Maintainer-email: Bill Bensing <bill@napecentral.com>
License: Apache License
Project-URL: Homepage, https://napecentral.com
Project-URL: Documentation, https://docs.napecentral.com
Project-URL: Repository, https://github.com/nape-not-another-policy-engine/nape-evaluator
Project-URL: Issues, https://github.com/nape-not-another-policy-engine/nape-evaluator/issues
Project-URL: Changelog, https://github.com/nape-not-another-policy-engine/nape-evaluator/blob/main/CHANGELOG.md
Keywords: nape,autonomous assurance,automated assurance,governance,governance engineering,goveng,audit,assurance,grc,internal audit,audit management,audit software,audit tools,assurnace software,assurance tools,grc software,compliance,cicd,ci,continuous integration,cd,continuous deployment,continuous delivery,devops,devsecops,security,infosec,information security,not another policy engine,policy engine,policy
Classifier: Development Status :: 5 - Production/Stable
Classifier: Environment :: Console
Classifier: Intended Audience :: Developers
Classifier: Intended Audience :: End Users/Desktop
Classifier: Intended Audience :: Financial and Insurance Industry
Classifier: Intended Audience :: Healthcare Industry
Classifier: Intended Audience :: Information Technology
Classifier: Intended Audience :: Legal Industry
Classifier: Intended Audience :: Other Audience
Classifier: Intended Audience :: System Administrators
Classifier: Intended Audience :: Telecommunications Industry
Classifier: License :: OSI Approved :: Apache Software License
Classifier: Natural Language :: English
Classifier: Operating System :: MacOS
Classifier: Operating System :: OS Independent
Classifier: Operating System :: POSIX :: Linux
Classifier: Programming Language :: Python
Classifier: Programming Language :: Python :: 3
Classifier: Topic :: File Formats :: JSON
Classifier: Topic :: Office/Business :: Financial
Classifier: Topic :: Security
Classifier: Topic :: Software Development
Classifier: Topic :: Software Development :: Build Tools
Classifier: Topic :: Software Development :: Embedded Systems
Classifier: Topic :: Software Development :: Pre-processors
Classifier: Topic :: Software Development :: Quality Assurance
Classifier: Topic :: Software Development :: Testing
Classifier: Topic :: Software Development :: Testing :: Acceptance
Classifier: Topic :: Software Development :: Testing :: BDD
Classifier: Topic :: Software Development :: Testing :: Unit
Classifier: Topic :: Software Development :: Version Control
Classifier: Topic :: Software Development :: Version Control :: Git
Classifier: Topic :: System
Classifier: Topic :: System :: Benchmark
Classifier: Topic :: System :: Filesystems
Classifier: Topic :: System :: Distributed Computing
Classifier: Topic :: System :: Logging
Classifier: Topic :: System :: Monitoring
Classifier: Topic :: System :: Networking
Classifier: Topic :: System :: Networking :: Monitoring
Classifier: Topic :: System :: Operating System
Classifier: Topic :: System :: Software Distribution
Classifier: Topic :: System :: Systems Administration
Classifier: Topic :: System :: Systems Administration :: Authentication/Directory
Classifier: Topic :: System :: Systems Administration :: Authentication/Directory :: LDAP
Classifier: Topic :: System :: Systems Administration :: Authentication/Directory :: NIS
Classifier: Topic :: Text Processing
Classifier: Topic :: Text Processing :: General
Classifier: Topic :: Text Processing :: Linguistic
Classifier: Topic :: Utilities
Requires-Python: >=3.0
License-File: LICENSE
